ilpdlsts/__init__.py
ilpdlsts-0.0.10.dist-info/licenses/LICENSE
ilpdlsts-0.0.10.dist-info/METADATA
ilpdlsts-0.0.10.dist-info/WHEEL
ilpdlsts-0.0.10.dist-info/top_level.txt
ilpdlsts-0.0.10.dist-info/RECORD
