Metadata-Version: 2.4
Name: ilpdlsts
Version: 0.0.10
Summary: Python Package for Santec Insertion Loss and Polarization Dependent Loss Swept Test System
Author: Santec Holdings Corporation
License-Expression: MIT
Project-URL: Homepage, https://github.com/santec-corporation/ilpdlsts-py
Project-URL: Repository, https://github.com/santec-corporation/ilpdlsts-py
Requires-Python: >=3.7
License-File: LICENSE
Dynamic: license-file
